autotime/__init__.py
autotime/_version.py
ipython_autotime_pst-1.0.dist-info/LICENSE
ipython_autotime_pst-1.0.dist-info/METADATA
ipython_autotime_pst-1.0.dist-info/WHEEL
ipython_autotime_pst-1.0.dist-info/top_level.txt
ipython_autotime_pst-1.0.dist-info/RECORD
